{
  "UC4hoj6ZAYMEEF2icXM745cw": {
    "ai": 2,
    "_total": 2,
    "_updatedAt": "2025-09-13T16:35:27.186Z"
  },
  "UCnDslcDrBIUhd5PcDM3BXTQ": {
    "ai": 1,
    "_total": 1,
    "_updatedAt": "2025-09-13T16:35:26.896Z"
  },
  "UCyLrrk5X1QR-OjNxiOVi3aw": {
    "ai": 1,
    "_total": 1,
    "_updatedAt": "2025-09-13T16:35:26.899Z"
  },
  "UChj6goRpbt_ojIIUhg3hL-A": {
    "review": 1,
    "_total": 1,
    "_updatedAt": "2025-09-13T16:35:28.262Z"
  },
  "UCqbeULJcuIuN-KJGxdzBIdQ": {
    "review": 1,
    "_total": 1,
    "_updatedAt": "2025-09-13T16:35:30.931Z"
  },
  "UCdtywaIs6rw9MU-6TgGvcFA": {
    "review": 1,
    "_total": 1,
    "_updatedAt": "2025-09-13T16:35:30.954Z"
  },
  "UCUzgcVDj2BFB3T7TCDlMhRw": {
    "review": 1,
    "_total": 1,
    "_updatedAt": "2025-09-13T16:35:30.955Z"
  },
  "UCtqa40wFjB0m84Jdo-puwrA": {
    "review": 1,
    "_total": 1,
    "_updatedAt": "2025-09-13T16:35:31.180Z"
  },
  "UCIW_XUuR3kGwJDpRsOh-EmQ": {
    "review": 1,
    "_total": 1,
    "_updatedAt": "2025-09-13T16:35:31.191Z"
  },
  "UCnnxmJmF03vucasp4c3Bepg": {
    "review": 1,
    "_total": 1,
    "_updatedAt": "2025-09-13T16:35:31.194Z"
  },
  "UCGDGw1dMotpPPWXC6ee_cZA": {
    "review": 1,
    "_total": 1,
    "_updatedAt": "2025-09-13T16:35:31.195Z"
  },
  "UCTTmtS2ljy1vyl_s-d_LEHQ": {
    "politics": 1,
    "_total": 1,
    "_updatedAt": "2025-09-13T16:35:32.119Z"
  },
  "UC4NImiQA2ZNmlafvhJFZGlQ": {
    "politics": 4,
    "_total": 4,
    "_updatedAt": "2025-09-13T16:35:32.320Z"
  },
  "UCKPbw2aFXXZtarxwq0wuQlA": {
    "politics": 3,
    "_total": 3,
    "_updatedAt": "2025-09-13T16:35:32.322Z"
  },
  "UCGrraKQiTF-ml0KqPQ8mrUA": {
    "politics": 1,
    "_total": 1,
    "_updatedAt": "2025-09-13T16:35:32.128Z"
  },
  "UCSd6jlFPB6iVG3eCTH7XJZA": {
    "politics": 1,
    "_total": 1,
    "_updatedAt": "2025-09-13T16:35:32.304Z"
  },
  "UCR0VAgd0w8QI7WWQ0E8Srdw": {
    "politics": 1,
    "_total": 1,
    "_updatedAt": "2025-09-13T16:35:32.312Z"
  },
  "UCcQTRi69dsVYHN3exePtZ1A": {
    "politics": 1,
    "_total": 1,
    "_updatedAt": "2025-09-13T16:35:32.317Z"
  },
  "UCu73jk-JW4p1ib01IC89Jyw": {
    "politics": 1,
    "_total": 1,
    "_updatedAt": "2025-09-13T16:35:32.321Z"
  },
  "UCvecmfA61gqueNxNx7Ti0gQ": {
    "entertainment": 2,
    "_total": 2,
    "_updatedAt": "2025-09-13T16:35:33.709Z"
  },
  "UCaihC7L_i5NjDay6i9AZDRg": {
    "entertainment": 1,
    "_total": 1,
    "_updatedAt": "2025-09-13T16:35:33.385Z"
  },
  "UCT3usBwYM36YFlJmsLY7bIA": {
    "entertainment": 3,
    "_total": 3,
    "_updatedAt": "2025-09-13T16:35:33.736Z"
  },
  "UCkinYTS9IHqOEwR1Sze2JTw": {
    "entertainment": 2,
    "_total": 2,
    "_updatedAt": "2025-09-13T16:35:33.408Z"
  },
  "UCF4Wxdo3inmxP-Y59wXDsFw": {
    "entertainment": 1,
    "_total": 1,
    "_updatedAt": "2025-09-13T16:35:33.409Z"
  },
  "UCUGsqdZ-Y-BOVsBW7bbZtLg": {
    "entertainment": 1,
    "_total": 1,
    "_updatedAt": "2025-09-13T16:35:33.717Z"
  },
  "UC1wGg05fTPH0L4Cvsr7wDIA": {
    "senior": 1,
    "_total": 1,
    "_updatedAt": "2025-09-13T16:35:34.791Z"
  },
  "UC-e5-NIxUXD6eKUEu-zSTNQ": {
    "senior": 2,
    "_total": 2,
    "_updatedAt": "2025-09-13T16:35:35.101Z"
  },
  "UC1jnSvRiKsOoi-tC2JKtVlA": {
    "senior": 1,
    "_total": 1,
    "_updatedAt": "2025-09-13T16:35:34.793Z"
  },
  "UCfNLAnyD4aG644l1wKzhnHQ": {
    "senior": 1,
    "_total": 1,
    "_updatedAt": "2025-09-13T16:35:34.799Z"
  },
  "UC6WWJnN9FjMlfErjUUs_5rQ": {
    "senior": 1,
    "_total": 1,
    "_updatedAt": "2025-09-13T16:35:34.801Z"
  },
  "UCOctcOkuoDU9ewg1kMwgcVg": {
    "senior": 1,
    "_total": 1,
    "_updatedAt": "2025-09-13T16:35:34.801Z"
  },
  "UC_-jI2xtnhyQmgAN2DZ620Q": {
    "senior": 1,
    "_total": 1,
    "_updatedAt": "2025-09-13T16:35:34.807Z"
  },
  "UC09Qq6bskfyxpWsDwWWNDRw": {
    "senior": 1,
    "_total": 1,
    "_updatedAt": "2025-09-13T16:35:34.812Z"
  },
  "UCeBxasYo6ZNeUzMA7_cS6FA": {
    "senior": 1,
    "_total": 1,
    "_updatedAt": "2025-09-13T16:35:35.090Z"
  },
  "UCCDesp2XqkYyZZG2LeFsR2g": {
    "senior": 1,
    "_total": 1,
    "_updatedAt": "2025-09-13T16:35:35.091Z"
  },
  "UCNhi3r8Pu5FG-DxHTg1cfUA": {
    "senior": 1,
    "_total": 1,
    "_updatedAt": "2025-09-13T16:35:35.094Z"
  },
  "UCxoFu3oPk66iUuu1HNK4PwQ": {
    "official": 1,
    "_total": 1,
    "_updatedAt": "2025-09-13T16:35:36.370Z"
  },
  "UCt4bWJILlEo1hvsR224ASyA": {
    "sports": 2,
    "_total": 2,
    "_updatedAt": "2025-09-13T16:35:37.728Z"
  },
  "UCvxUjIDPpFivXNjVXniopGw": {
    "game": 1,
    "_total": 1,
    "_updatedAt": "2025-09-13T16:35:37.401Z"
  },
  "UCBQ04pkCI2-O-3rIawL1Dyg": {
    "sports": 1,
    "_total": 1,
    "_updatedAt": "2025-09-13T16:35:37.416Z"
  },
  "UCCu7BCdADOLbGAsTNoVgOBA": {
    "sports": 3,
    "_total": 3,
    "_updatedAt": "2025-09-13T16:35:37.730Z"
  },
  "UCjseqv83urpRnK88hy5kMgg": {
    "sports": 1,
    "_total": 1,
    "_updatedAt": "2025-09-13T16:35:37.708Z"
  },
  "UC96xuaT-9Ayl2L-CBt_-wgQ": {
    "sports": 2,
    "_total": 2,
    "_updatedAt": "2025-09-13T16:35:37.721Z"
  }
}